beef/__init__.py
beef/examples.py
beef/general.py
beef/io.py
beef/modal.py
beef/newmark.py
beef/nlfe2d.py
beef/plot.py
beef/rotation.py
beef/fe/__init__.py
beef/fe/analysis.py
beef/fe/constraint.py
beef/fe/eldef.py
beef/fe/element.py
beef/fe/features.py
beef/fe/force.py
beef/fe/node.py
beef/fe/results.py
beef/fe/section.py
beef/fe/step.py
beefpy-0.6.3.dist-info/LICENSE
beefpy-0.6.3.dist-info/METADATA
beefpy-0.6.3.dist-info/WHEEL
beefpy-0.6.3.dist-info/top_level.txt
beefpy-0.6.3.dist-info/RECORD
