Metadata-Version: 2.2
Name: beefpy
Version: 0.6.3
Summary: BEam Elements Framework (BEEF)
Author-email: "Knut A. Kvaale" <knut.a.kvale@ntnu.no>
License: MIT License
Project-URL: repository, https://github.com/knutankv/beef
Project-URL: documentation, https://knutankv.github.io/beef/
Classifier: License :: OSI Approved :: MIT License
Classifier: Operating System :: OS Independent
Classifier: Programming Language :: Python :: 3
Classifier: Topic :: Scientific/Engineering
Requires-Python: >=3.6
License-File: LICENSE
Requires-Dist: scipy
Requires-Dist: numpy
Requires-Dist: matplotlib
Requires-Dist: tqdm
Requires-Dist: trame
Requires-Dist: pyvista
Requires-Dist: dill
